{
    "form": {
        "category": "5",
        "cells": [
            {
                "row": 1,
                "column": 2,
                "box": [
                    143,
                    259,
                    2408,
                    238,
                    2409,
                    306,
                    141,
                    354
                ],
                "words": [
                    {
                        "boundingbox": [
                            143,
                            259,
                            2409,
                            259,
                            2409,
                            306,
                            259,
                            2409
                        ],
                        "type": "printedChinese"
                    }
                ]
            },
            {
                "row": 2,
                "column": 1,
                "box": [
                    380,
                    352,
                    1050,
                    348,
                    1050,
                    452,
                    382,
                    456
                ],
                "words": []
            },
            {
                "row": 2,
                "column": 3,
                "box": [
                    2238,
                    335,
                    2294,
                    335,
                    2296,
                    442,
                    2240,
                    442
                ],
                "words": []
            },
            {
                "row": 2,
                "column": 4,
                "box": [
                    1050,
                    348,
                    2238,
                    335,
                    2240,
                    442,
                    1050,
                    452
                ],
                "words": []
            },
            {
                "row": 2,
                "column": 5,
                "box": [
                    2294,
                    335,
                    2351,
                    335,
                    2352,
                    442,
                    2296,
                    442
                ],
                "words": []
            },
            {
                "row": 2,
                "column": 6,
                "box": [
                    2351,
                    335,
                    2411,
                    335,
                    2412,
                    442,
                    2352,
                    442
                ],
                "words": []
            },
            {
                "row": 2,
                "column": 10,
                "box": [
                    141,
                    354,
                    380,
                    352,
                    382,
                    456,
                    142,
                    458
                ],
                "words": [
                    {
                        "boundingbox": [
                            141,
                            354,
                            382,
                            354,
                            382,
                            456,
                            354,
                            382
                        ],
                        "type": "printedChinese"
                    }
                ]
            },
            {
                "row": 4,
                "column": 1,
                "box": [
                    1050,
                    452,
                    2240,
                    442,
                    2242,
                    547,
                    1050,
                    556
                ],
                "words": []
            },
            {
                "row": 4,
                "column": 3,
                "box": [
                    382,
                    456,
                    1050,
                    452,
                    1050,
                    556,
                    382,
                    560
                ],
                "words": []
            },
            {
                "row": 4,
                "column": 4,
                "box": [
                    2240,
                    442,
                    2296,
                    442,
                    2297,
                    547,
                    2242,
                    547
                ],
                "words": []
            },
            {
                "row": 4,
                "column": 5,
                "box": [
                    142,
                    458,
                    382,
                    456,
                    382,
                    560,
                    143,
                    562
                ],
                "words": [
                    {
                        "boundingbox": [
                            142,
                            458,
                            382,
                            458,
                            382,
                            560,
                            458,
                            382
                        ],
                        "type": "printedChinese"
                    }
                ]
            },
            {
                "row": 4,
                "column": 6,
                "box": [
                    2296,
                    442,
                    2352,
                    442,
                    2354,
                    548,
                    2297,
                    547
                ],
                "words": []
            },
            {
                "row": 4,
                "column": 7,
                "box": [
                    2352,
                    442,
                    2412,
                    442,
                    2413,
                    548,
                    2354,
                    548
                ],
                "words": []
            },
            {
                "row": 6,
                "column": 1,
                "box": [
                    143,
                    601,
                    2410,
                    586,
                    2410,
                    653,
                    142,
                    668
                ],
                "words": [
                    {
                        "boundingbox": [
                            143,
                            601,
                            2410,
                            601,
                            2410,
                            653,
                            601,
                            2410
                        ],
                        "type": "printedChinese"
                    }
                ]
            },
            {
                "row": 7,
                "column": 1,
                "box": [
                    379,
                    695,
                    1050,
                    692,
                    1050,
                    796,
                    381,
                    799
                ],
                "words": []
            },
            {
                "row": 7,
                "column": 2,
                "box": [
                    2242,
                    681,
                    2297,
                    681,
                    2298,
                    788,
                    2242,
                    788
                ],
                "words": []
            },
            {
                "row": 7,
                "column": 3,
                "box": [
                    1050,
                    692,
                    2242,
                    681,
                    2242,
                    788,
                    1050,
                    796
                ],
                "words": []
            },
            {
                "row": 7,
                "column": 4,
                "box": [
                    2297,
                    681,
                    2353,
                    681,
                    2354,
                    788,
                    2298,
                    788
                ],
                "words": []
            },
            {
                "row": 7,
                "column": 5,
                "box": [
                    2353,
                    681,
                    2412,
                    682,
                    2412,
                    788,
                    2354,
                    788
                ],
                "words": []
            },
            {
                "row": 7,
                "column": 8,
                "box": [
                    141,
                    696,
                    405,
                    708,
                    381,
                    799,
                    142,
                    801
                ],
                "words": []
            },
            {
                "row": 9,
                "column": 1,
                "box": [
                    1050,
                    796,
                    2242,
                    788,
                    2242,
                    893,
                    1050,
                    901
                ],
                "words": []
            },
            {
                "row": 9,
                "column": 2,
                "box": [
                    381,
                    799,
                    1050,
                    796,
                    1050,
                    901,
                    407,
                    893
                ],
                "words": []
            },
            {
                "row": 9,
                "column": 3,
                "box": [
                    142,
                    801,
                    381,
                    799,
                    382,
                    904,
                    143,
                    904
                ],
                "words": []
            },
            {
                "row": 9,
                "column": 5,
                "box": [
                    2242,
                    788,
                    2298,
                    788,
                    2298,
                    892,
                    2242,
                    893
                ],
                "words": []
            },
            {
                "row": 9,
                "column": 6,
                "box": [
                    2298,
                    788,
                    2354,
                    788,
                    2354,
                    892,
                    2298,
                    892
                ],
                "words": []
            },
            {
                "row": 9,
                "column": 7,
                "box": [
                    2354,
                    788,
                    2412,
                    788,
                    2414,
                    893,
                    2354,
                    892
                ],
                "words": []
            },
            {
                "row": 11,
                "column": 1,
                "box": [
                    144,
                    957,
                    2412,
                    944,
                    2412,
                    1012,
                    143,
                    1023
                ],
                "words": [
                    {
                        "boundingbox": [
                            144,
                            957,
                            2412,
                            957,
                            2412,
                            1012,
                            957,
                            2412
                        ],
                        "type": "printedChinese"
                    }
                ]
            },
            {
                "row": 12,
                "column": 1,
                "box": [
                    379,
                    1051,
                    1050,
                    1048,
                    1052,
                    1154,
                    381,
                    1155
                ],
                "words": []
            },
            {
                "row": 12,
                "column": 2,
                "box": [
                    2240,
                    1041,
                    2296,
                    1041,
                    2297,
                    1147,
                    2241,
                    1148
                ],
                "words": []
            },
            {
                "row": 12,
                "column": 3,
                "box": [
                    1050,
                    1048,
                    2240,
                    1041,
                    2241,
                    1148,
                    1052,
                    1154
                ],
                "words": []
            },
            {
                "row": 12,
                "column": 4,
                "box": [
                    2296,
                    1041,
                    2354,
                    1042,
                    2354,
                    1147,
                    2297,
                    1147
                ],
                "words": []
            },
            {
                "row": 12,
                "column": 5,
                "box": [
                    2354,
                    1042,
                    2413,
                    1041,
                    2414,
                    1148,
                    2354,
                    1147
                ],
                "words": []
            },
            {
                "row": 12,
                "column": 6,
                "box": [
                    142,
                    1052,
                    408,
                    1066,
                    381,
                    1155,
                    144,
                    1156
                ],
                "words": []
            },
            {
                "row": 14,
                "column": 1,
                "box": [
                    1052,
                    1154,
                    2241,
                    1148,
                    2242,
                    1252,
                    1052,
                    1256
                ],
                "words": []
            },
            {
                "row": 14,
                "column": 2,
                "box": [
                    381,
                    1155,
                    1052,
                    1154,
                    1052,
                    1256,
                    382,
                    1258
                ],
                "words": []
            },
            {
                "row": 14,
                "column": 3,
                "box": [
                    144,
                    1156,
                    381,
                    1155,
                    382,
                    1258,
                    144,
                    1259
                ],
                "words": []
            },
            {
                "row": 14,
                "column": 4,
                "box": [
                    2241,
                    1148,
                    2297,
                    1147,
                    2298,
                    1252,
                    2242,
                    1252
                ],
                "words": []
            },
            {
                "row": 14,
                "column": 5,
                "box": [
                    2297,
                    1147,
                    2354,
                    1147,
                    2355,
                    1250,
                    2298,
                    1252
                ],
                "words": []
            },
            {
                "row": 14,
                "column": 6,
                "box": [
                    2354,
                    1147,
                    2414,
                    1148,
                    2415,
                    1250,
                    2355,
                    1250
                ],
                "words": []
            },
            {
                "row": 16,
                "column": 1,
                "box": [
                    144,
                    1300,
                    2412,
                    1290,
                    2412,
                    1359,
                    143,
                    1366
                ],
                "words": [
                    {
                        "boundingbox": [
                            144,
                            1300,
                            2412,
                            1300,
                            2412,
                            1359,
                            1300,
                            2412
                        ],
                        "type": "printedChinese"
                    }
                ]
            },
            {
                "row": 17,
                "column": 1,
                "box": [
                    379,
                    1394,
                    1050,
                    1392,
                    1050,
                    1498,
                    381,
                    1498
                ],
                "words": []
            },
            {
                "row": 17,
                "column": 2,
                "box": [
                    2240,
                    1387,
                    2296,
                    1387,
                    2297,
                    1494,
                    2241,
                    1494
                ],
                "words": []
            },
            {
                "row": 17,
                "column": 3,
                "box": [
                    1050,
                    1392,
                    2240,
                    1387,
                    2241,
                    1494,
                    1050,
                    1498
                ],
                "words": []
            },
            {
                "row": 17,
                "column": 4,
                "box": [
                    2296,
                    1387,
                    2353,
                    1388,
                    2354,
                    1494,
                    2297,
                    1494
                ],
                "words": []
            },
            {
                "row": 17,
                "column": 5,
                "box": [
                    2353,
                    1388,
                    2413,
                    1388,
                    2414,
                    1494,
                    2354,
                    1494
                ],
                "words": []
            },
            {
                "row": 17,
                "column": 6,
                "box": [
                    142,
                    1395,
                    379,
                    1394,
                    381,
                    1498,
                    143,
                    1499
                ],
                "words": []
            },
            {
                "row": 20,
                "column": 1,
                "box": [
                    1050,
                    1498,
                    2241,
                    1494,
                    2242,
                    1598,
                    1050,
                    1602
                ],
                "words": []
            },
            {
                "row": 20,
                "column": 2,
                "box": [
                    381,
                    1498,
                    1050,
                    1498,
                    1050,
                    1602,
                    407,
                    1594
                ],
                "words": []
            },
            {
                "row": 20,
                "column": 3,
                "box": [
                    143,
                    1499,
                    381,
                    1498,
                    382,
                    1602,
                    144,
                    1602
                ],
                "words": []
            },
            {
                "row": 20,
                "column": 4,
                "box": [
                    2241,
                    1494,
                    2297,
                    1494,
                    2297,
                    1598,
                    2242,
                    1598
                ],
                "words": []
            },
            {
                "row": 20,
                "column": 5,
                "box": [
                    2297,
                    1494,
                    2354,
                    1494,
                    2354,
                    1598,
                    2297,
                    1598
                ],
                "words": []
            },
            {
                "row": 20,
                "column": 6,
                "box": [
                    2354,
                    1494,
                    2414,
                    1494,
                    2414,
                    1598,
                    2354,
                    1598
                ],
                "words": []
            },
            {
                "row": 22,
                "column": 1,
                "box": [
                    146,
                    1660,
                    2413,
                    1654,
                    2414,
                    1721,
                    144,
                    1726
                ],
                "words": [
                    {
                        "boundingbox": [
                            146,
                            1660,
                            2414,
                            1660,
                            2414,
                            1721,
                            1660,
                            2414
                        ],
                        "type": "printedChinese"
                    }
                ]
            },
            {
                "row": 23,
                "column": 1,
                "box": [
                    380,
                    1754,
                    1051,
                    1753,
                    1052,
                    1858,
                    407,
                    1850
                ],
                "words": []
            },
            {
                "row": 23,
                "column": 2,
                "box": [
                    2242,
                    1749,
                    2297,
                    1749,
                    2298,
                    1856,
                    2242,
                    1856
                ],
                "words": []
            },
            {
                "row": 23,
                "column": 3,
                "box": [
                    1051,
                    1753,
                    2242,
                    1749,
                    2242,
                    1856,
                    1052,
                    1858
                ],
                "words": []
            },
            {
                "row": 23,
                "column": 4,
                "box": [
                    2297,
                    1749,
                    2355,
                    1749,
                    2356,
                    1856,
                    2298,
                    1856
                ],
                "words": []
            },
            {
                "row": 23,
                "column": 5,
                "box": [
                    2355,
                    1749,
                    2415,
                    1749,
                    2416,
                    1856,
                    2356,
                    1856
                ],
                "words": []
            },
            {
                "row": 23,
                "column": 6,
                "box": [
                    144,
                    1754,
                    380,
                    1754,
                    382,
                    1858,
                    145,
                    1859
                ],
                "words": []
            },
            {
                "row": 25,
                "column": 1,
                "box": [
                    1052,
                    1858,
                    2242,
                    1856,
                    2243,
                    1959,
                    1051,
                    1962
                ],
                "words": []
            },
            {
                "row": 25,
                "column": 2,
                "box": [
                    382,
                    1858,
                    1052,
                    1858,
                    1051,
                    1962,
                    408,
                    1953
                ],
                "words": []
            },
            {
                "row": 25,
                "column": 3,
                "box": [
                    145,
                    1859,
                    382,
                    1858,
                    383,
                    1963,
                    146,
                    1963
                ],
                "words": []
            },
            {
                "row": 25,
                "column": 4,
                "box": [
                    2242,
                    1856,
                    2298,
                    1856,
                    2298,
                    1959,
                    2243,
                    1959
                ],
                "words": []
            },
            {
                "row": 25,
                "column": 6,
                "box": [
                    2298,
                    1856,
                    2356,
                    1856,
                    2356,
                    1959,
                    2298,
                    1959
                ],
                "words": []
            },
            {
                "row": 25,
                "column": 7,
                "box": [
                    2356,
                    1856,
                    2416,
                    1856,
                    2416,
                    1959,
                    2356,
                    1959
                ],
                "words": []
            },
            {
                "row": 27,
                "column": 1,
                "box": [
                    145,
                    2003,
                    2412,
                    1998,
                    2413,
                    2065,
                    144,
                    2069
                ],
                "words": [
                    {
                        "boundingbox": [
                            145,
                            2003,
                            2413,
                            2003,
                            2413,
                            2065,
                            2003,
                            2413
                        ],
                        "type": "printedChinese"
                    }
                ]
            },
            {
                "row": 29,
                "column": 1,
                "box": [
                    379,
                    2097,
                    1050,
                    2096,
                    1050,
                    2202,
                    381,
                    2202
                ],
                "words": []
            },
            {
                "row": 29,
                "column": 2,
                "box": [
                    2240,
                    2093,
                    2296,
                    2094,
                    2297,
                    2200,
                    2241,
                    2200
                ],
                "words": []
            },
            {
                "row": 29,
                "column": 3,
                "box": [
                    1050,
                    2096,
                    2240,
                    2093,
                    2241,
                    2200,
                    1050,
                    2202
                ],
                "words": []
            },
            {
                "row": 29,
                "column": 4,
                "box": [
                    2296,
                    2094,
                    2354,
                    2094,
                    2354,
                    2200,
                    2297,
                    2200
                ],
                "words": []
            },
            {
                "row": 29,
                "column": 5,
                "box": [
                    2354,
                    2094,
                    2414,
                    2094,
                    2414,
                    2200,
                    2354,
                    2200
                ],
                "words": []
            },
            {
                "row": 29,
                "column": 6,
                "box": [
                    143,
                    2097,
                    379,
                    2097,
                    381,
                    2202,
                    144,
                    2202
                ],
                "words": []
            },
            {
                "row": 31,
                "column": 1,
                "box": [
                    1050,
                    2202,
                    2241,
                    2200,
                    2241,
                    2304,
                    1050,
                    2306
                ],
                "words": []
            },
            {
                "row": 31,
                "column": 2,
                "box": [
                    381,
                    2202,
                    1050,
                    2202,
                    1050,
                    2306,
                    408,
                    2298
                ],
                "words": []
            },
            {
                "row": 31,
                "column": 3,
                "box": [
                    144,
                    2202,
                    381,
                    2202,
                    382,
                    2306,
                    144,
                    2306
                ],
                "words": []
            },
            {
                "row": 31,
                "column": 4,
                "box": [
                    2241,
                    2200,
                    2297,
                    2200,
                    2297,
                    2304,
                    2241,
                    2304
                ],
                "words": []
            },
            {
                "row": 31,
                "column": 6,
                "box": [
                    2297,
                    2200,
                    2354,
                    2200,
                    2355,
                    2304,
                    2297,
                    2304
                ],
                "words": []
            },
            {
                "row": 31,
                "column": 7,
                "box": [
                    2354,
                    2200,
                    2414,
                    2200,
                    2415,
                    2304,
                    2355,
                    2304
                ],
                "words": []
            },
            {
                "row": 33,
                "column": 1,
                "box": [
                    150,
                    2360,
                    2418,
                    2357,
                    2418,
                    2424,
                    149,
                    2426
                ],
                "words": [
                    {
                        "boundingbox": [
                            150,
                            2360,
                            2418,
                            2360,
                            2418,
                            2424,
                            2360,
                            2418
                        ],
                        "type": "printedChinese"
                    }
                ]
            },
            {
                "row": 34,
                "column": 1,
                "box": [
                    384,
                    2454,
                    1054,
                    2454,
                    1054,
                    2559,
                    411,
                    2551
                ],
                "words": []
            },
            {
                "row": 34,
                "column": 2,
                "box": [
                    2244,
                    2452,
                    2300,
                    2452,
                    2301,
                    2557,
                    2245,
                    2557
                ],
                "words": []
            },
            {
                "row": 34,
                "column": 3,
                "box": [
                    1054,
                    2454,
                    2244,
                    2452,
                    2245,
                    2557,
                    1054,
                    2559
                ],
                "words": []
            },
            {
                "row": 34,
                "column": 4,
                "box": [
                    2300,
                    2452,
                    2358,
                    2452,
                    2359,
                    2557,
                    2301,
                    2557
                ],
                "words": []
            },
            {
                "row": 34,
                "column": 5,
                "box": [
                    2358,
                    2452,
                    2419,
                    2452,
                    2419,
                    2557,
                    2359,
                    2557
                ],
                "words": []
            },
            {
                "row": 34,
                "column": 6,
                "box": [
                    148,
                    2455,
                    384,
                    2454,
                    386,
                    2559,
                    149,
                    2560
                ],
                "words": []
            },
            {
                "row": 36,
                "column": 1,
                "box": [
                    1054,
                    2559,
                    2245,
                    2557,
                    2246,
                    2661,
                    1053,
                    2662
                ],
                "words": []
            },
            {
                "row": 36,
                "column": 2,
                "box": [
                    386,
                    2559,
                    1054,
                    2559,
                    1053,
                    2662,
                    413,
                    2657
                ],
                "words": []
            },
            {
                "row": 36,
                "column": 3,
                "box": [
                    149,
                    2560,
                    386,
                    2559,
                    387,
                    2662,
                    150,
                    2663
                ],
                "words": []
            },
            {
                "row": 36,
                "column": 4,
                "box": [
                    2245,
                    2557,
                    2301,
                    2557,
                    2301,
                    2661,
                    2246,
                    2661
                ],
                "words": []
            },
            {
                "row": 36,
                "column": 7,
                "box": [
                    2301,
                    2557,
                    2359,
                    2557,
                    2359,
                    2660,
                    2301,
                    2661
                ],
                "words": []
            },
            {
                "row": 36,
                "column": 8,
                "box": [
                    2359,
                    2557,
                    2419,
                    2557,
                    2420,
                    2660,
                    2359,
                    2660
                ],
                "words": []
            },
            {
                "row": 38,
                "column": 1,
                "box": [
                    149,
                    2704,
                    2416,
                    2700,
                    2416,
                    2767,
                    148,
                    2770
                ],
                "words": [
                    {
                        "boundingbox": [
                            149,
                            2704,
                            2416,
                            2704,
                            2416,
                            2767,
                            2704,
                            2416
                        ],
                        "type": "printedChinese"
                    }
                ]
            },
            {
                "row": 39,
                "column": 1,
                "box": [
                    383,
                    2798,
                    1052,
                    2798,
                    1052,
                    2902,
                    414,
                    2888
                ],
                "words": []
            },
            {
                "row": 39,
                "column": 2,
                "box": [
                    2244,
                    2795,
                    2299,
                    2795,
                    2300,
                    2900,
                    2244,
                    2901
                ],
                "words": []
            },
            {
                "row": 39,
                "column": 3,
                "box": [
                    1052,
                    2798,
                    2244,
                    2795,
                    2244,
                    2901,
                    1052,
                    2902
                ],
                "words": []
            },
            {
                "row": 39,
                "column": 4,
                "box": [
                    2299,
                    2795,
                    2357,
                    2796,
                    2358,
                    2900,
                    2300,
                    2900
                ],
                "words": []
            },
            {
                "row": 39,
                "column": 5,
                "box": [
                    2357,
                    2796,
                    2417,
                    2795,
                    2418,
                    2900,
                    2358,
                    2900
                ],
                "words": []
            },
            {
                "row": 39,
                "column": 6,
                "box": [
                    147,
                    2799,
                    383,
                    2798,
                    384,
                    2902,
                    148,
                    2904
                ],
                "words": []
            },
            {
                "row": 41,
                "column": 1,
                "box": [
                    1052,
                    2902,
                    2244,
                    2901,
                    2244,
                    3004,
                    1051,
                    3005
                ],
                "words": []
            },
            {
                "row": 41,
                "column": 2,
                "box": [
                    384,
                    2902,
                    1052,
                    2902,
                    1051,
                    3005,
                    416,
                    2993
                ],
                "words": []
            },
            {
                "row": 41,
                "column": 3,
                "box": [
                    148,
                    2904,
                    384,
                    2902,
                    386,
                    3006,
                    148,
                    3006
                ],
                "words": []
            },
            {
                "row": 41,
                "column": 4,
                "box": [
                    2244,
                    2901,
                    2300,
                    2900,
                    2300,
                    3004,
                    2244,
                    3004
                ],
                "words": []
            },
            {
                "row": 41,
                "column": 5,
                "box": [
                    2300,
                    2900,
                    2358,
                    2900,
                    2358,
                    3004,
                    2300,
                    3004
                ],
                "words": []
            },
            {
                "row": 41,
                "column": 6,
                "box": [
                    2358,
                    2900,
                    2418,
                    2900,
                    2418,
                    3004,
                    2358,
                    3004
                ],
                "words": []
            },
            {
                "row": 43,
                "column": 1,
                "box": [
                    151,
                    3036,
                    2418,
                    3032,
                    2419,
                    3098,
                    150,
                    3103
                ],
                "words": [
                    {
                        "boundingbox": [
                            151,
                            3036,
                            2419,
                            3036,
                            2419,
                            3098,
                            3036,
                            2419
                        ],
                        "type": "printedChinese"
                    }
                ]
            },
            {
                "row": 44,
                "column": 1,
                "box": [
                    386,
                    3130,
                    1054,
                    3130,
                    1054,
                    3234,
                    415,
                    3224
                ],
                "words": []
            },
            {
                "row": 44,
                "column": 2,
                "box": [
                    2246,
                    3127,
                    2301,
                    3127,
                    2302,
                    3232,
                    2246,
                    3232
                ],
                "words": []
            },
            {
                "row": 44,
                "column": 3,
                "box": [
                    1054,
                    3130,
                    2246,
                    3127,
                    2246,
                    3232,
                    1054,
                    3234
                ],
                "words": []
            },
            {
                "row": 44,
                "column": 4,
                "box": [
                    2301,
                    3127,
                    2360,
                    3127,
                    2360,
                    3232,
                    2302,
                    3232
                ],
                "words": []
            },
            {
                "row": 44,
                "column": 5,
                "box": [
                    2360,
                    3127,
                    2420,
                    3127,
                    2420,
                    3232,
                    2360,
                    3232
                ],
                "words": []
            },
            {
                "row": 44,
                "column": 6,
                "box": [
                    149,
                    3131,
                    386,
                    3130,
                    388,
                    3235,
                    150,
                    3236
                ],
                "words": []
            },
            {
                "row": 46,
                "column": 1,
                "box": [
                    1054,
                    3234,
                    2246,
                    3232,
                    2247,
                    3336,
                    1054,
                    3338
                ],
                "words": []
            },
            {
                "row": 46,
                "column": 2,
                "box": [
                    388,
                    3235,
                    1054,
                    3234,
                    1054,
                    3338,
                    418,
                    3329
                ],
                "words": []
            },
            {
                "row": 46,
                "column": 3,
                "box": [
                    150,
                    3236,
                    388,
                    3235,
                    389,
                    3340,
                    150,
                    3340
                ],
                "words": []
            },
            {
                "row": 46,
                "column": 4,
                "box": [
                    2246,
                    3232,
                    2302,
                    3232,
                    2302,
                    3336,
                    2247,
                    3336
                ],
                "words": []
            },
            {
                "row": 46,
                "column": 5,
                "box": [
                    2302,
                    3232,
                    2360,
                    3232,
                    2360,
                    3335,
                    2302,
                    3336
                ],
                "words": []
            },
            {
                "row": 46,
                "column": 6,
                "box": [
                    2360,
                    3232,
                    2420,
                    3232,
                    2420,
                    3335,
                    2360,
                    3335
                ],
                "words": []
            }
        ]
    }
}